mininet_topology_yaml-0.1.5.dist-info/DESCRIPTION.rst
mininet_topology_yaml-0.1.5.dist-info/LICENSE.txt
mininet_topology_yaml-0.1.5.dist-info/METADATA
mininet_topology_yaml-0.1.5.dist-info/RECORD
mininet_topology_yaml-0.1.5.dist-info/WHEEL
mininet_topology_yaml-0.1.5.dist-info/entry_points.txt
mininet_topology_yaml-0.1.5.dist-info/metadata.json
mininet_topology_yaml-0.1.5.dist-info/top_level.txt
mn_topo/__init__.py
mn_topo/api.py
mn_topo/cli.py
mn_topo/core/__init__.py
mn_topo/core/cli_types.py
mn_topo/core/constants.py
mn_topo/core/dc.py
mn_topo/core/mn_topology.py
mn_topo/core/table.py
mn_topo/core/utility.py
tests/__init__.py
tests/test_api.py
tests/core/__init__.py
tests/core/test_cli_types.py
tests/core/test_dc.py
tests/core/test_table.py
tests/core/test_utility.py
