Metadata-Version: 1.1
Name: mininet-topology-yaml
Version: 0.1.5
Summary: Mininet specific topology generator and parser
Home-page: UNKNOWN
Author: Lumina NetDev
Author-email: oss-dev@luminanetworks.com
License: UNKNOWN
Platform: UNKNOWN
Classifier: Development Status :: 2 - Pre-Alpha
Classifier: Programming Language :: Python
Classifier: Programming Language :: Python :: 2
Classifier: Programming Language :: Python :: 2.7
Classifier: Programming Language :: Python :: 3
Classifier: Programming Language :: Python :: 3.4
Classifier: Programming Language :: Python :: 3.5
